{
  "aulas": [
    {
      "disciplina": "Disciplina X",
      "professor": "Prof X",
      "turma": "Turma X"
    },
    {
      "disciplina": "Disciplina X",
      "professor": "Prof X",
      "turma": "Turma X"
    },
    {
      "disciplina": "Disciplina Y",
      "professor": "Prof X",
      "turma": "Turma X"
    },
    {
      "disciplina": "Disciplina P",
      "professor": "Prof X",
      "turma": "Turma X"
    },
    {
      "disciplina": "Disciplina Z",
      "professor": "Prof Y",
      "turma": "Turma X"
    }
  ],
  "professores": [
    {
      "id": "Prof X",
      "periodos": [
        {
          "diaSemana": 1,
          "periodo": 1
        },
        {
          "diaSemana": 1,
          "periodo": 2
        },
        {
          "diaSemana": 3,
          "periodo": 2
        }
      ]
    },
    {
      "id": "Prof Y",
      "periodos": [
        {
          "diaSemana": 1,
          "periodo": 1
        },
        {
          "diaSemana": 1,
          "periodo": 2
        }
      ]
    }
  ]
}
